haige_pyqt/__init__.py
haige_pyqt/Lib/__init__.py
haige_pyqt/Lib/win32Lib.py
haige_pyqt/auto_start/__init__.py
haige_pyqt/auto_start/linux.py
haige_pyqt/auto_start/macos.py
haige_pyqt/auto_start/win.py
haige_pyqt/resources/__init__.py
haige_pyqt/runtime/__init__.py
haige_pyqt/runtime/app.py
haige_pyqt/runtime/conf.py
haige_pyqt/straper/__init__.py
haige_pyqt/straper/guard.py
haige_pyqt/straper/manager.py
haige_pyqt/uis/__init__.py
haige_pyqt/uis/about.py
haige_pyqt/widgets/__init__.py
haige_pyqt/widgets/about.py
haige_pyqt/widgets/common/__init__.py
haige_pyqt/widgets/common/doubleSlider.py
haige_pyqt/widgets/common/exclusiver.py
haige_pyqt/widgets/mixins/__init__.py
haige_pyqt/widgets/mixins/styles.py
tests/__init__.py
haige_pyqt-1.0.6.dist-info/METADATA
haige_pyqt-1.0.6.dist-info/WHEEL
haige_pyqt-1.0.6.dist-info/top_level.txt
haige_pyqt-1.0.6.dist-info/RECORD
