Metadata-Version: 2.1
Name: haige-pyqt
Version: 1.0.6
Summary: 江湖海哥的常用 pyqt 封装通用包。
Author: 喜欢吃白米饭
Author-email: gzhehai@foxmail.com
Classifier: Programming Language :: Python :: 3
Classifier: License :: OSI Approved :: MIT License
Classifier: Operating System :: OS Independent
Requires-Python: >=3.6
Requires-Dist: PyQt5 (>=5.15.9)
Requires-Dist: astunparse (>=1.6.3)
Requires-Dist: pywin32 (>=310)
